zcloud/__init__.py
zcloud/aws/__init__.py
zcloud/aws/firehose.py
zcloud/aws/s3.py
zcloud/aws/secret_manager.py
zcloud/aws/sqs.py
zcloud/aws/ssm.py
zcloud/aws/helpers/__init__.py
zcloud/aws/helpers/aws_client_factory.py
zcloud/aws/helpers/aws_secret_provider_manager.py
zpy_cloud_utils-1.1.2.dist-info/LICENSE
zpy_cloud_utils-1.1.2.dist-info/METADATA
zpy_cloud_utils-1.1.2.dist-info/WHEEL
zpy_cloud_utils-1.1.2.dist-info/top_level.txt
zpy_cloud_utils-1.1.2.dist-info/RECORD
