Metadata-Version: 2.1
Name: zpy-cloud-utils
Version: 1.1.2
Summary: Helper layer for apis development with Python and Flask
Home-page: https://github.com/NoeCruzMW
Author: Noé Cruz | linkedin.com/in/zurckz/
Author-email: zurckz.services@gmail.com
Classifier: Programming Language :: Python :: 3
Classifier: License :: OSI Approved :: MIT License
Classifier: Operating System :: OS Independent
Requires-Python: >=3.6
License-File: LICENSE
Requires-Dist: zpy-api-core
